django_otp/__init__.py
django_otp/admin.py
django_otp/conf.py
django_otp/decorators.py
django_otp/forms.py
django_otp/middleware.py
django_otp/models.py
django_otp/oath.py
django_otp/qr.py
django_otp/util.py
django_otp/views.py
django_otp/locale/de/LC_MESSAGES/django.mo
django_otp/locale/de/LC_MESSAGES/django.po
django_otp/locale/es/LC_MESSAGES/django.mo
django_otp/locale/es/LC_MESSAGES/django.po
django_otp/locale/fr/LC_MESSAGES/django.mo
django_otp/locale/fr/LC_MESSAGES/django.po
django_otp/locale/pt_BR/LC_MESSAGES/django.mo
django_otp/locale/pt_BR/LC_MESSAGES/django.po
django_otp/locale/pt_PT/LC_MESSAGES/django.mo
django_otp/locale/pt_PT/LC_MESSAGES/django.po
django_otp/plugins/__init__.py
django_otp/plugins/otp_email/__init__.py
django_otp/plugins/otp_email/admin.py
django_otp/plugins/otp_email/apps.py
django_otp/plugins/otp_email/conf.py
django_otp/plugins/otp_email/models.py
django_otp/plugins/otp_email/migrations/0001_initial.py
django_otp/plugins/otp_email/migrations/0002_sidechanneldevice_email.py
django_otp/plugins/otp_email/migrations/0003_emaildevice_email.py
django_otp/plugins/otp_email/migrations/0004_throttling.py
django_otp/plugins/otp_email/migrations/0005_emaildevice_last_generated_timestamp.py
django_otp/plugins/otp_email/migrations/0006_add_timestamps.py
django_otp/plugins/otp_email/migrations/__init__.py
django_otp/plugins/otp_email/templates/otp/email/token.txt
django_otp/plugins/otp_hotp/__init__.py
django_otp/plugins/otp_hotp/admin.py
django_otp/plugins/otp_hotp/apps.py
django_otp/plugins/otp_hotp/models.py
django_otp/plugins/otp_hotp/migrations/0001_initial.py
django_otp/plugins/otp_hotp/migrations/0002_auto_20190420_0723.py
django_otp/plugins/otp_hotp/migrations/0003_add_timestamps.py
django_otp/plugins/otp_hotp/migrations/__init__.py
django_otp/plugins/otp_hotp/templates/otp_hotp/admin/config.html
django_otp/plugins/otp_static/__init__.py
django_otp/plugins/otp_static/admin.py
django_otp/plugins/otp_static/apps.py
django_otp-1.6.2.dist-info/METADATA
django_otp-1.6.2.dist-info/WHEEL
django_otp-1.6.2.dist-info/licenses/LICENSE
django_otp-1.6.2.dist-info/RECORD
