Metadata-Version: 2.4
Name: django-otp
Version: 1.6.2
Summary: A pluggable framework for adding two-factor authentication to Django using one-time passwords.
Project-URL: Homepage, https://github.com/django-otp/django-otp
Project-URL: Documentation, https://django-otp-official.readthedocs.io/
Author-email: Peter Sagerson <psagers@ignorare.net>
License-Expression: Unlicense
License-File: LICENSE
Classifier: Development Status :: 5 - Production/Stable
Classifier: Framework :: Django
Classifier: Framework :: Django :: 4.2
Classifier: Framework :: Django :: 5.1
Classifier: Framework :: Django :: 5.2
Classifier: Intended Audience :: Developers
Classifier: License :: OSI Approved :: The Unlicense (Unlicense)
Classifier: Programming Language :: Python :: 3
Classifier: Programming Language :: Python :: 3 :: Only
Classifier: Topic :: Security
Classifier: Topic :: Software Development :: Libraries :: Python Modules
Requires-Python: >=3.7
Requires-Dist: django>=4.2
Provides-Extra: qrcode
Requires-Dist: qrcode; extra == 'qrcode'
Provides-Extra: segno
Requires-Dist: segno; extra == 'segno'
